linked_services/__about__.py
linked_services/__init__.py
linked_services/admin.py
linked_services/apps.py
linked_services/models.py
linked_services/settings.py
linked_services/core/actions.py
linked_services/core/decorators.py
linked_services/core/exceptions.py
linked_services/core/i18n.py
linked_services/core/service.py
linked_services/core/settings.py
linked_services/core/shorteners.py
linked_services/core/utils.py
linked_services/django/__init__.py
linked_services/django/actions.py
linked_services/django/admin.py
linked_services/django/middlewares.py
linked_services/django/models.py
linked_services/django/receivers.py
linked_services/django/service.py
linked_services/django/signals.py
linked_services/django/tasks.py
linked_services/django/urls.py
linked_services/management/__init__.py
linked_services/management/commands/__init__.py
linked_services/management/commands/first_party_webhooks.py
linked_services/management/commands/get_first_party_ids.py
linked_services/management/commands/sign_jwt.py
linked_services/management/commands/sign_request.py
linked_services/migrations/0001_initial.py
linked_services/migrations/__init__.py
linked_services/pytest/__init__.py
linked_services/pytest/django/__init__.py
linked_services/pytest/django/fixtures/__init__.py
linked_services/pytest/django/fixtures/service.py
linked_services/rest_framework/__init__.py
linked_services/rest_framework/decorators.py
linked_services/rest_framework/types.py
linked_services/rest_framework/views.py
linked_services/templates/app-not-found.html
linked_services/templates/authorize.html
linked_services/templates/button.html
linked_services/templates/scopes.html
linked_services/templatetags/__init__.py
linked_services/templatetags/button.py
linked_services/templatetags/scopes.py
linked_services-1.3.1.dist-info/METADATA
linked_services-1.3.1.dist-info/WHEEL
linked_services-1.3.1.dist-info/licenses/LICENSE.txt
linked_services-1.3.1.dist-info/RECORD
