Metadata-Version: 2.3
Name: linked-services
Version: 1.3.1
Project-URL: Documentation, https://breatheco-de.github.io/linked-services-django-plugin/
Project-URL: Issues, https://github.com/breatheco-de/linked-services-django-plugin/issues
Project-URL: Source, https://github.com/breatheco-de/linked-services-django-plugin
Author-email: jefer94 <jdefreitaspinto@gmail.com>
License: LGPL-3.0-or-later
Classifier: Development Status :: 5 - Production/Stable
Classifier: Framework :: Django :: 4.2
Classifier: Framework :: Django :: 5.0
Classifier: License :: OSI Approved :: GNU Lesser General Public License v3 or later (LGPLv3+)
Classifier: Programming Language :: Python
Classifier: Programming Language :: Python :: 3.10
Classifier: Programming Language :: Python :: 3.11
Classifier: Programming Language :: Python :: 3.12
Classifier: Programming Language :: Python :: Implementation :: CPython
Classifier: Programming Language :: Python :: Implementation :: PyPy
Classifier: Topic :: Software Development :: Libraries
Requires-Python: >=3.10
Requires-Dist: asgiref
Requires-Dist: celery-task-manager
Requires-Dist: cryptography
Requires-Dist: pyjwt
Requires-Dist: python-slugify
Provides-Extra: aiohttp
Requires-Dist: aiodns; extra == 'aiohttp'
Requires-Dist: aiohttp; extra == 'aiohttp'
Requires-Dist: brotli; extra == 'aiohttp'
Provides-Extra: django
Requires-Dist: adrf; extra == 'django'
Requires-Dist: celery-task-manager[django]; extra == 'django'
Requires-Dist: django; extra == 'django'
Requires-Dist: djangorestframework; extra == 'django'
Provides-Extra: httpx
Requires-Dist: brotli; extra == 'httpx'
Requires-Dist: h11; extra == 'httpx'
Requires-Dist: httpcore; extra == 'httpx'
Requires-Dist: httpx; extra == 'httpx'
Requires-Dist: idna; extra == 'httpx'
Provides-Extra: requests
Requires-Dist: brotli; extra == 'requests'
Requires-Dist: requests; extra == 'requests'
